pystanssh/__init__.py
pystanssh/base.py
pystanssh/pystan.py
pystanssh-0.1.3.dist-info/LICENSE
pystanssh-0.1.3.dist-info/METADATA
pystanssh-0.1.3.dist-info/WHEEL
pystanssh-0.1.3.dist-info/top_level.txt
pystanssh-0.1.3.dist-info/RECORD
