Metadata-Version: 2.1
Name: pystanssh
Version: 0.1.3
Summary: PyStan I/O between servers with ssh
Home-page: https://github.com/jhand1993/pystanssh
Author: Jared Hand
Author-email: jared.hand1993@gmail.com
License: GPL V3
Platform: UNKNOWN
Requires-Dist: paramiko
Requires-Dist: numpy
